gamma_viewer/__init__.py
gamma_viewer/gamma_viewer.py
gamma_viewer/static/extension.js
gamma_viewer-0.2.1.data/data/etc/jupyter/nbconfig/notebook.d/gamma_viewer.json
gamma_viewer-0.2.1.data/data/share/jupyter/nbextensions/gamma_viewer/extension.js
gamma_viewer-0.2.1.dist-info/LICENSE
gamma_viewer-0.2.1.dist-info/METADATA
gamma_viewer-0.2.1.dist-info/WHEEL
gamma_viewer-0.2.1.dist-info/top_level.txt
gamma_viewer-0.2.1.dist-info/RECORD
