Metadata-Version: 2.1
Name: gamma-viewer
Version: 0.2.1
Summary: Interactive Translator UI for the Jupyter notebook, using React.
Home-page: https://github.com/ranking-agent/gamma-viewer
Author: CoVar Applied Technologies
License: MIT
Keywords: ipython,jupyter,widgets,Translator,plotting,react
Platform: UNKNOWN
Classifier: Intended Audience :: Developers
Classifier: Intended Audience :: Science/Research
Classifier: Topic :: Multimedia :: Graphics
Requires-Dist: jupyter-react (~=0.1.3)
